{"title": "Blackthorn cocktails", "tags": [{"tag": "Christmas"}], "planning": {"prep_time": "PT5M", "cook_time": null, "total_time": null, "serves": null}, "ingredients": [{"item": "60ml Sipsmith Sloe Gin"}, {"item": "30ml Martini Rosso"}, {"item": "1 dash Angostura bitter"}, {"item": "Ice cubes"}, {"item": "Lemon peel"}], "instructions": [{"step": "Measure the ingredients into a cocktail shaker, add ice and stir."}, {"step": "Strain the mixture into a chilled glass (keep it in the fridge for an hour or so beforehand)."}, {"step": "Squeeze the lemon peel over the drink to release its oil, then drop it into the glass and serve."}], "nutrition": null, "image_url": "//d1v30bmd12dhid.cloudfront.net/static/version6/content/dam/waitrose/recipes/images/b/400x400_blackthorncocktail.jpg/_jcr_content/renditions/cq5dam.thumbnail.400.400.png"}